tinyplaylists/__init__.py
tinyplaylists/main.py
tinyplaylists/playlist.py
tinyplaylists/track.py
tinyplaylists-0.1.2.dist-info/WHEEL
tinyplaylists-0.1.2.dist-info/METADATA
tinyplaylists-0.1.2.dist-info/RECORD
