Metadata-Version: 2.1
Name: tinyplaylists
Version: 0.1.2
Summary: A tiny library to organize audio files
Author: platers
Author-email: platers81@gmail.com
Requires-Python: >=3.7,<4.0
Classifier: Programming Language :: Python :: 3
Classifier: Programming Language :: Python :: 3.10
Classifier: Programming Language :: Python :: 3.7
Classifier: Programming Language :: Python :: 3.8
Classifier: Programming Language :: Python :: 3.9
Requires-Dist: music-tag (>=0.4.3,<0.5.0)
